ggcmpy/__init__.py
ggcmpy/_jrrle.cpython-310-x86_64-linux-gnu.so
ggcmpy/_version.py
ggcmpy/_version.pyi
ggcmpy/iono.py
ggcmpy/jrrle_array.py
ggcmpy/jrrle_backend.py
ggcmpy/jrrle_store.py
ggcmpy/openggcm.py
ggcmpy/plot_polar.py
ggcmpy/py.typed
ggcmpy/timeseries.py
ggcmpy/backends/jrrle/__init__.py
ggcmpy/backends/jrrle/_fortfile.F90
ggcmpy/backends/jrrle/_jrrle.F90
ggcmpy/backends/jrrle/constants.F90
ggcmpy/backends/jrrle/f2py_interface.F90
ggcmpy/backends/jrrle/fortran_file.py
ggcmpy/backends/jrrle/ground_perturbation.F90
ggcmpy/backends/jrrle/iono_psol.F90
ggcmpy/backends/jrrle/jrrle_file.py
ggcmpy/backends/jrrle/new_cotr.F90
ggcmpy/backends/jrrle/simple-death.F90
ggcmpy/backends/jrrle/util.py
ggcmpy/sample/coupling0001.iof.000030
ggcmpy/sample/coupling0001.iof.000060
ggcmpy/sample/sample_jrrle.3df.001200
ggcmpy/sample/sample_jrrle.grid2
ggcmpy/sample/sample_jrrle.iof.010491
ggcmpy/sample/sample_jrrle.py_0.001200
ggcmpy/sample/cir07_19970227_liang_norcm/tmp.minvar/om1997.3
ggcmpy/sample/cir07_19970227_liang_norcm/tmp.minvar/om1997.4
ggcmpy/sample/cir07_19970227_liang_norcm/tmp.minvar/om1997.5
ggcmpy/sample/cir07_19970227_liang_norcm/tmp.minvar/om1997.bl
ggcmpy/sample/cir07_19970227_liang_norcm/tmp.minvar/om1997.bm
ggcmpy/sample/cir07_19970227_liang_norcm/tmp.minvar/om1997.bn
ggcmpy/sample/cir07_19970227_liang_norcm/tmp.minvar/om1997.bxgse
ggcmpy/sample/cir07_19970227_liang_norcm/tmp.minvar/om1997.bxtra
ggcmpy/sample/cir07_19970227_liang_norcm/tmp.minvar/om1997.bxtra0
ggcmpy/sample/cir07_19970227_liang_norcm/tmp.minvar/om1997.bygse
ggcmpy/sample/cir07_19970227_liang_norcm/tmp.minvar/om1997.bytra
ggcmpy/sample/cir07_19970227_liang_norcm/tmp.minvar/om1997.bytra0
ggcmpy/sample/cir07_19970227_liang_norcm/tmp.minvar/om1997.bzgse
ggcmpy/sample/cir07_19970227_liang_norcm/tmp.minvar/om1997.bztra
ggcmpy/sample/cir07_19970227_liang_norcm/tmp.minvar/om1997.bztra0
ggcmpy/sample/cir07_19970227_liang_norcm/tmp.minvar/om1997.nxtra
ggcmpy-0.1.0a8.dist-info/METADATA
ggcmpy-0.1.0a8.dist-info/WHEEL
ggcmpy-0.1.0a8.dist-info/entry_points.txt
ggcmpy-0.1.0a8.dist-info/RECORD
ggcmpy-0.1.0a8.dist-info/licenses/LICENSE
