Metadata-Version: 2.1
Name: ggcmpy
Version: 0.1.0a8
Summary: Python utilities for the OpenGGCM Global Magnetosphere Code
Author: Kai Germaschewski, Jimmy Raeder, Matt Gilson, Kristofer Maynard
Maintainer-Email: Kai Germaschewski <kai.germaschewski@unh.edu>
License: 
Classifier: Development Status :: 1 - Planning
Classifier: Intended Audience :: Science/Research
Classifier: Intended Audience :: Developers
Classifier: License :: OSI Approved :: Apache Software License
Classifier: Operating System :: OS Independent
Classifier: Programming Language :: Python
Classifier: Programming Language :: Python :: 3
Classifier: Programming Language :: Python :: 3 :: Only
Classifier: Programming Language :: Python :: 3.10
Classifier: Programming Language :: Python :: 3.11
Classifier: Programming Language :: Python :: 3.12
Classifier: Programming Language :: Python :: 3.13
Classifier: Topic :: Scientific/Engineering
Project-URL: Homepage, https://github.com/unh-hpc/ggcmpy
Project-URL: Bug Tracker, https://github.com/unh-hpc/ggcmpy/issues
Project-URL: Discussions, https://github.com/unh-hpc/ggcmpy/discussions
Project-URL: Changelog, https://github.com/unh-hpc/ggcmpy/releases
Requires-Python: >=3.10
Requires-Dist: xarray<2025.07
Requires-Dist: typing-extensions
Requires-Dist: dask
Requires-Dist: matplotlib
Provides-Extra: test
Requires-Dist: pytest>=6; extra == "test"
Requires-Dist: pytest-cov>=3; extra == "test"
Requires-Dist: xarray-adios2; extra == "test"
Provides-Extra: dev
Requires-Dist: pytest>=6; extra == "dev"
Requires-Dist: pytest-cov>=3; extra == "dev"
Requires-Dist: xarray-adios2; extra == "dev"
Requires-Dist: pyspedas; extra == "dev"
Requires-Dist: nox; extra == "dev"
Requires-Dist: pre-commit; extra == "dev"
Provides-Extra: adios2
Requires-Dist: xarray-adios2; extra == "adios2"
Provides-Extra: docs
Requires-Dist: sphinx>=7.0; extra == "docs"
Requires-Dist: myst_parser>=0.13; extra == "docs"
Requires-Dist: sphinx_copybutton; extra == "docs"
Requires-Dist: sphinx_autodoc_typehints; extra == "docs"
Requires-Dist: nbsphinx>=0.9; extra == "docs"
Requires-Dist: xarray; extra == "docs"
Requires-Dist: ipykernel; extra == "docs"
Requires-Dist: matplotlib; extra == "docs"
Requires-Dist: sphinx-book-theme; extra == "docs"
Requires-Dist: pyspedas; extra == "docs"
